pyBSDate/ADCalendar.py
pyBSDate/BSCalendar.py
pyBSDate/BSDate.py
pyBSDate/BaseCalendar.py
pyBSDate/DateConverter.py
pyBSDate/DateMap.py
pyBSDate/__init__.py
pyBSDate/utilities.py
pyBSDate/wrappers.py
pybsdate-0.3.2.dist-info/METADATA
pybsdate-0.3.2.dist-info/WHEEL
pybsdate-0.3.2.dist-info/top_level.txt
pybsdate-0.3.2.dist-info/RECORD
