Metadata-Version: 2.4
Name: pyBSDate
Version: 0.3.2
Summary: Python BS date conversion utility
Home-page: https://github.com/SushilShrestha/pyBSDate
Download-URL: https://github.com/SushilShrestha/pyBSDate/tarball/0.3.2
Author: sushil
Author-email: afahocci@gmail.com
License: MIT
Classifier: Programming Language :: Python :: 2.7
Classifier: Programming Language :: Python :: 3.7
Classifier: Topic :: Software Development :: Libraries
Classifier: Topic :: Utilities
Dynamic: author
Dynamic: author-email
Dynamic: classifier
Dynamic: description
Dynamic: description-content-type
Dynamic: download-url
Dynamic: home-page
Dynamic: license
Dynamic: summary
